setup.py
botchat/__init__.py
botchat/command_line.py
botchat.egg-info/PKG-INFO
botchat.egg-info/SOURCES.txt
botchat.egg-info/dependency_links.txt
botchat.egg-info/entry_points.txt
botchat.egg-info/not-zip-safe
botchat.egg-info/requires.txt
botchat.egg-info/top_level.txt