Metadata-Version: 1.0
Name: botchat
Version: 0.3
Summary: Let a bot chat on your behalf on whatsapp
Home-page: https://github.com/lakshaykalbhor/Whatsapp-BotChat
Author: Lakshay Kalbhor
Author-email: lakshaykalbhor@gmail.com
License: MIT
Platform: UNKNOWN
